slurm_job/__init__.py
slurm_job/__main__.py
slurm_job/core.py
slurm_job/local.py
slurm_job/slurm.py
slurm_job/utils.py
slurm_job/xenon_slurm.py
slurm_job-0.1.0.dist-info/METADATA
slurm_job-0.1.0.dist-info/WHEEL
slurm_job-0.1.0.dist-info/entry_points.txt
slurm_job-0.1.0.dist-info/RECORD
