Metadata-Version: 2.1
Name: slurm_job
Version: 0.1.0
Summary: 
Author: Yibo Wei
Author-email: david_wyb2001@outlook.com
Requires-Python: >=3.9,<4.0
Classifier: Programming Language :: Python :: 3
Classifier: Programming Language :: Python :: 3.9
Classifier: Programming Language :: Python :: 3.10
Classifier: Programming Language :: Python :: 3.11
Classifier: Programming Language :: Python :: 3.12
Requires-Dist: cloudpickle (>=3.0.0,<4.0.0)
Requires-Dist: rich (>=13.7.1,<14.0.0)
Requires-Dist: sh (>=2.0.6,<3.0.0)
Requires-Dist: simple-slurm (>=0.2.7,<0.3.0)
Requires-Dist: watchdog (>=4.0.0,<5.0.0)
